comparable_pattern/__init__.py
comparable_pattern/_comparable_pattern.py
comparable_pattern/py.typed
comparable_pattern/version.py
comparable_pattern-0.0.4.dist-info/LICENSE
comparable_pattern-0.0.4.dist-info/METADATA
comparable_pattern-0.0.4.dist-info/WHEEL
comparable_pattern-0.0.4.dist-info/top_level.txt
comparable_pattern-0.0.4.dist-info/RECORD
