Metadata-Version: 2.1
Name: comparable_pattern
Version: 0.0.4
Summary: A comparable string / regex object for flexible string comparisons.
Author-email: Rudolf Byker <rudolfbyker@gmail.com>
Project-URL: repository, https://github.com/AutoActuary/comparable_pattern
Classifier: Programming Language :: Python :: 3
Classifier: License :: Other/Proprietary License
Classifier: Operating System :: OS Independent
Requires-Python: >=3.11
License-File: LICENSE
